{
  "_date": "2024-10-25 20:22:13.884000",
  "_total": 48871,
  "_total_diff": 361,
  "barbet": 0,
  "barbet_diff": 0,
  "blueline": 12430,
  "blueline_diff": 115,
  "bonito": 1860,
  "bonito_diff": 89,
  "bramble": 1752,
  "bramble_diff": 0,
  "coral": 2926,
  "coral_diff": 1,
  "crosshatch": 9322,
  "crosshatch_diff": 35,
  "flame": 3869,
  "flame_diff": 8,
  "liber": 1490,
  "liber_diff": 2,
  "miatoll": 361,
  "miatoll_diff": 35,
  "redfin": 4735,
  "redfin_diff": 70,
  "rosemary": 792,
  "rosemary_diff": 21,
  "sargo": 3415,
  "sargo_diff": 9,
  "sunfish": 3564,
  "sunfish_diff": 24,
  "taimen": 3508,
  "taimen_diff": 8,
  "walleye": 0,
  "walleye_diff": 0
}