{
    "barbet": 0,
    "blueline": 3158,
    "blueline_diff": 12,
    "bonito": 494,
    "bonito_diff": 0,
    "bramble": 191,
    "bramble_diff": 3,
    "coral": 728,
    "coral_diff": 3,
    "crosshatch": 2016,
    "crosshatch_diff": 11,
    "flame": 670,
    "flame_diff": 6,
    "liber": 283,
    "liber_diff": 1,
    "miatoll": 361,
    "miatoll_diff": 35,
    "redfin": 758,
    "redfin_diff": 12,
    "rosemary": 792,
    "rosemary_diff": 21,
    "sargo": 1361,
    "sargo_diff": 3,
    "sunfish": 1076,
    "sunfish_diff": 3,
    "taimen": 649,
    "taimen_diff": 8,
    "walleye": 0
}